lorem_pysum/__init__.py
lorem_pysum/_generator.py
lorem_pysum/py.typed
lorem_pysum-1.4.11.dist-info/LICENSE
lorem_pysum-1.4.11.dist-info/METADATA
lorem_pysum-1.4.11.dist-info/WHEEL
lorem_pysum-1.4.11.dist-info/RECORD
